tests/__init__.py
tests/test.py
yggdrasil/__init__.py
yggdrasil/app_manager.py
yggdrasil/scripts.py
yggdrasil/data/ls_tools.txt
yggdrasil/data/template_launcher_local.txt
yggdrasil/data/template_launcher_web.txt
yggdrasil/data/template_settings.yaml
yggdrasil/drivers/__init__.py
yggdrasil/drivers/app_generic.py
yggdrasil/drivers/app_local.py
yggdrasil/drivers/app_web.py
yggdrasil/utilities/__init__.py
yggdrasil/utilities/logger.py
yggdrasil/utilities/minor.py
yggdrasil/utilities/settings.py
ud_yggdrasil-2.0.0.dist-info/LICENSE
ud_yggdrasil-2.0.0.dist-info/METADATA
ud_yggdrasil-2.0.0.dist-info/WHEEL
ud_yggdrasil-2.0.0.dist-info/entry_points.txt
ud_yggdrasil-2.0.0.dist-info/top_level.txt
ud_yggdrasil-2.0.0.dist-info/RECORD
