Metadata-Version: 2.1
Name: ud-yggdrasil
Version: 2.0.0
Summary: Apps handler for in-house python scripts
Home-page: https://github.com/um-en/yggdrasil
Author: Umbriel Draken
Author-email: umbriel.draken@gmail.com
License: MIT
Keywords: yggdrasil,drivers,virtual,environment
Platform: UNKNOWN
Classifier: License :: OSI Approved :: MIT License
Classifier: Programming Language :: Python :: 3.9
Classifier: Development Status :: 3 - Alpha
Classifier: Intended Audience :: Developers
Classifier: Natural Language :: English
Classifier: Operating System :: Microsoft :: Windows :: Windows 10
Requires-Dist: pyyaml
Requires-Dist: ud-dist-meta (>=1.0.3)
